sdk/sdk.py
python_sdk_sarat_rafay-0.0.1.dist-info/METADATA
python_sdk_sarat_rafay-0.0.1.dist-info/WHEEL
python_sdk_sarat_rafay-0.0.1.dist-info/licenses/LICENSE
python_sdk_sarat_rafay-0.0.1.dist-info/RECORD
