Metadata-Version: 2.1
Name: python-sdk_sarat-rafay
Version: 0.0.1
Summary: Rafay workflow handler Python function SDK
Project-URL: Homepage, https://github.com/RafaySystems/function-templates
Project-URL: Issues, https://github.com/RafaySystems/function-templates/issues
Author-email: Bheema Sarat Chandra Kaki <sarat@rafay.co>
License-File: LICENSE
Classifier: License :: OSI Approved :: MIT License
Classifier: Operating System :: OS Independent
Classifier: Programming Language :: Python :: 3
Requires-Python: >=3.11
